Cellist/Cellpose.py
Cellist/IO.py
Cellist/Imputation.py
Cellist/Plot.py
Cellist/Registration.py
Cellist/Segmentation.py
Cellist/Segmentation_tune.py
Cellist/Utility.py
Cellist/Watershed.py
Cellist/__init__.py
Cellist/version.py
cellist-1.1.1.data/scripts/cellist
cellist-1.1.1.dist-info/licenses/LICENSE
cellist-1.1.1.dist-info/METADATA
cellist-1.1.1.dist-info/WHEEL
cellist-1.1.1.dist-info/entry_points.txt
cellist-1.1.1.dist-info/top_level.txt
cellist-1.1.1.dist-info/RECORD
